odoo/addons/agreement_legal/README.rst
odoo/addons/agreement_legal/__init__.py
odoo/addons/agreement_legal/__manifest__.py
odoo/addons/agreement_legal/data/agreement_stage.xml
odoo/addons/agreement_legal/data/agreement_type.xml
odoo/addons/agreement_legal/data/cron.xml
odoo/addons/agreement_legal/data/ir_sequence.xml
odoo/addons/agreement_legal/demo/demo.xml
odoo/addons/agreement_legal/i18n/agreement_legal.pot
odoo/addons/agreement_legal/i18n/es.po
odoo/addons/agreement_legal/i18n/fr.po
odoo/addons/agreement_legal/i18n/pt.po
odoo/addons/agreement_legal/i18n/pt_BR.po
odoo/addons/agreement_legal/i18n/pt_PT.po
odoo/addons/agreement_legal/i18n/zh_CN.po
odoo/addons/agreement_legal/migrations/13.0.1.0.0/post-migration.py
odoo/addons/agreement_legal/migrations/13.0.1.0.0/pre-migration.py
odoo/addons/agreement_legal/models/__init__.py
odoo/addons/agreement_legal/models/agreement.py
odoo/addons/agreement_legal/models/agreement_appendix.py
odoo/addons/agreement_legal/models/agreement_clause.py
odoo/addons/agreement_legal/models/agreement_line.py
odoo/addons/agreement_legal/models/agreement_recital.py
odoo/addons/agreement_legal/models/agreement_section.py
odoo/addons/agreement_legal/models/agreement_stage.py
odoo/addons/agreement_legal/models/agreement_subtype.py
odoo/addons/agreement_legal/models/agreement_type.py
odoo/addons/agreement_legal/models/res_config_settings.py
odoo/addons/agreement_legal/models/res_partner.py
odoo/addons/agreement_legal/readme/CONFIGURE.rst
odoo/addons/agreement_legal/readme/CONTRIBUTORS.rst
odoo/addons/agreement_legal/readme/CREDITS.rst
odoo/addons/agreement_legal/readme/DESCRIPTION.rst
odoo/addons/agreement_legal/readme/ROADMAP.rst
odoo/addons/agreement_legal/readme/USAGE.rst
odoo/addons/agreement_legal/report/agreement.xml
odoo/addons/agreement_legal/security/ir.model.access.csv
odoo/addons/agreement_legal/security/res_groups.xml
odoo/addons/agreement_legal/static/description/icon.png
odoo/addons/agreement_legal/static/description/icon.svg
odoo13_addon_agreement_legal-13.0.2.5.1.dist-info/METADATA
odoo13_addon_agreement_legal-13.0.2.5.1.dist-info/WHEEL
odoo13_addon_agreement_legal-13.0.2.5.1.dist-info/top_level.txt
odoo13_addon_agreement_legal-13.0.2.5.1.dist-info/RECORD
